cotton_bs5/__init__.py
cotton_bs5/apps.py
cotton_bs5/static/_variables.scss
cotton_bs5/static/bs5/_accordion.scss
cotton_bs5/static/bs5/_alert.scss
cotton_bs5/static/bs5/_badge.scss
cotton_bs5/static/bs5/_breadcrumb.scss
cotton_bs5/static/bs5/_button-group.scss
cotton_bs5/static/bs5/_buttons.scss
cotton_bs5/static/bs5/_card.scss
cotton_bs5/static/bs5/_carousel.scss
cotton_bs5/static/bs5/_close.scss
cotton_bs5/static/bs5/_containers.scss
cotton_bs5/static/bs5/_dropdown.scss
cotton_bs5/static/bs5/_forms.scss
cotton_bs5/static/bs5/_functions.scss
cotton_bs5/static/bs5/_grid.scss
cotton_bs5/static/bs5/_helpers.scss
cotton_bs5/static/bs5/_images.scss
cotton_bs5/static/bs5/_list-group.scss
cotton_bs5/static/bs5/_maps.scss
cotton_bs5/static/bs5/_mixins.scss
cotton_bs5/static/bs5/_modal.scss
cotton_bs5/static/bs5/_nav.scss
cotton_bs5/static/bs5/_navbar.scss
cotton_bs5/static/bs5/_offcanvas.scss
cotton_bs5/static/bs5/_pagination.scss
cotton_bs5/static/bs5/_placeholders.scss
cotton_bs5/static/bs5/_popover.scss
cotton_bs5/static/bs5/_progress.scss
cotton_bs5/static/bs5/_reboot.scss
cotton_bs5/static/bs5/_root.scss
cotton_bs5/static/bs5/_spinners.scss
cotton_bs5/static/bs5/_tables.scss
cotton_bs5/static/bs5/_toasts.scss
cotton_bs5/static/bs5/_tooltip.scss
cotton_bs5/static/bs5/_transitions.scss
cotton_bs5/static/bs5/_type.scss
cotton_bs5/static/bs5/_utilities.scss
cotton_bs5/static/bs5/_variables-dark.scss
cotton_bs5/static/bs5/_variables.scss
cotton_bs5/static/bs5/bootstrap-grid.scss
cotton_bs5/static/bs5/bootstrap-reboot.scss
cotton_bs5/static/bs5/bootstrap-utilities.scss
cotton_bs5/static/bs5/bootstrap.scss
cotton_bs5/static/bs5/forms/_floating-labels.scss
cotton_bs5/static/bs5/forms/_form-check.scss
cotton_bs5/static/bs5/forms/_form-control.scss
cotton_bs5/static/bs5/forms/_form-range.scss
cotton_bs5/static/bs5/forms/_form-select.scss
cotton_bs5/static/bs5/forms/_form-text.scss
cotton_bs5/static/bs5/forms/_input-group.scss
cotton_bs5/static/bs5/forms/_labels.scss
django_cotton_bs5-0.5.1.dist-info/LICENSE
django_cotton_bs5-0.5.1.dist-info/METADATA
django_cotton_bs5-0.5.1.dist-info/WHEEL
django_cotton_bs5-0.5.1.dist-info/RECORD
