Metadata-Version: 2.1
Name: django-cotton-bs5
Version: 0.5.1
Summary: Bootstrap 5 components for use with Django Cotton.
License: MIT
Author: Sam
Author-email: samuel.scott.jennings@gmail.com
Requires-Python: >=3.10,<4.0
Classifier: License :: OSI Approved :: MIT License
Classifier: Programming Language :: Python :: 3
Classifier: Programming Language :: Python :: 3.10
Classifier: Programming Language :: Python :: 3.11
Classifier: Programming Language :: Python :: 3.12
Provides-Extra: django-compressor
Requires-Dist: django-compressor (>=4.5.1,<5.0.0) ; extra == "django-compressor"
Requires-Dist: django-cotton (>=2.3.1)
Requires-Dist: django-libsass (>=0.9,<0.10)
